exsclaim/README.md
exsclaim/__init__.py
exsclaim/__main__.py
exsclaim/caption.py
exsclaim/config.py
exsclaim/exceptions.py
exsclaim/figure.py
exsclaim/journal.py
exsclaim/notifications.py
exsclaim/pdf.py
exsclaim/pipeline.py
exsclaim/tool.py
exsclaim/version.py
exsclaim/version.pyi
exsclaim/api/__init__.py
exsclaim/api/__main__.py
exsclaim/api/config.py
exsclaim/api/middleware.py
exsclaim/api/models.py
exsclaim/api/settings.py
exsclaim/api/routers/__init__.py
exsclaim/api/routers/v1.py
exsclaim/captions/__init__.py
exsclaim/captions/ollama_llms.py
exsclaim/captions/openai_llms.py
exsclaim/dashboard/__init__.py
exsclaim/dashboard/__main__.py
exsclaim/dashboard/config.py
exsclaim/dashboard/assets/Argonnelablogo-White.png
exsclaim/dashboard/assets/Argonnelablogo.png
exsclaim/dashboard/assets/ExsclaimLogo-Black.png
exsclaim/dashboard/assets/ExsclaimLogo-Inverted.png
exsclaim/dashboard/assets/ExsclaimLogo.png
exsclaim/dashboard/assets/exsclaim.css
exsclaim/dashboard/assets/favicon.ico
exsclaim/dashboard/assets/recolor.py
exsclaim/dashboard/components/__init__.py
exsclaim/dashboard/components/api_client.py
exsclaim/dashboard/components/common.py
exsclaim/dashboard/components/homepage.py
exsclaim/dashboard/components/layout.py
exsclaim/dashboard/components/query.py
exsclaim/dashboard/components/resultpage.py
exsclaim/db/__init__.py
exsclaim/db/models.py
exsclaim/db/postgres.py
exsclaim/figures/__init__.py
exsclaim/figures/classes.py
exsclaim/figures/masks.py
exsclaim/figures/transformations.py
exsclaim/figures/config/scale_label_reader.json
exsclaim/figures/config/yolov3_default_master.cfg
exsclaim/figures/config/yolov3_default_subfig.cfg
exsclaim/figures/models/__init__.py
exsclaim/figures/models/crnn.py
exsclaim/figures/models/network.py
exsclaim/figures/models/yolo_layer.py
exsclaim/figures/models/yolov3.py
exsclaim/figures/scale/__init__.py
exsclaim/figures/scale/coco_eval.py
exsclaim/figures/scale/coco_utils.py
exsclaim/figures/scale/corpus.txt
exsclaim-2.4.1.dist-info/licenses/LICENSE
exsclaim-2.4.1.dist-info/METADATA
exsclaim-2.4.1.dist-info/WHEEL
exsclaim-2.4.1.dist-info/entry_points.txt
exsclaim-2.4.1.dist-info/top_level.txt
exsclaim-2.4.1.dist-info/RECORD
