Metadata-Version: 2.4
Name: exsclaim
Version: 2.4.1
Summary: EXSCLAIM! is a library for the automatic EXtraction, Separation, and Caption-based natural Language Annotation of IMages from scientific figures.
Author-email: "Eric Schwenker, Trevor Spreadbury, Weixin Jiang, Maria Chan, Len Washington III" <developer@materialeyes.org>
License: MIT License
Project-URL: Homepage, https://exsclaim.materialeyes.org
Project-URL: Source, https://github.com/MaterialEyes/exsclaim2.0
Project-URL: Documentation, https://github.com/MaterialEyes/exsclaim2.0/wiki
Project-URL: Issues, https://github.com/MaterialEyes/exsclaim2.0/issues
Project-URL: Paper, https://arxiv.org/abs/2103.10631
Classifier: Development Status :: 4 - Beta
Classifier: Environment :: Console
Classifier: Environment :: Web Environment
Classifier: Framework :: Dash
Classifier: Framework :: FastAPI
Classifier: Intended Audience :: Science/Research
Classifier: License :: OSI Approved :: MIT License
Classifier: Operating System :: OS Independent
Classifier: Programming Language :: JavaScript
Classifier: Programming Language :: Python :: 3.11
Classifier: Programming Language :: Python :: 3.12
Classifier: Programming Language :: Python :: 3.13
Classifier: Topic :: Scientific/Engineering :: Image Processing
Classifier: Topic :: Text Processing
Requires-Python: >=3.13.2
License-File: LICENSE
Requires-Dist: loguru==0.7.3
Requires-Dist: numpy==2.2.6
Requires-Dist: opencv-contrib-python-headless==4.12.0.88
Requires-Dist: Pillow==11.3.0
Requires-Dist: ultralytics==8.3.170
Requires-Dist: aiohttp==3.12.15
Requires-Dist: httpx==0.28.1
Requires-Dist: brotli==1.1.0
Requires-Dist: selenium==4.34.2
Requires-Dist: selenium-stealth==1.0.6
Requires-Dist: urllib3==2.5.0
Requires-Dist: asyncpg==0.30.0
Requires-Dist: beautifulsoup4==4.13.4
Requires-Dist: soupsieve==2.7
Requires-Dist: deepdiff==8.5.0
Requires-Dist: pycocotools==2.0.10
Requires-Dist: pytz==2025.2
Requires-Dist: typing_extensions==4.14.0
Requires-Dist: PyYAML==6.0.2
Requires-Dist: pymupdf==1.26.3
Requires-Dist: torch==2.7.1
Requires-Dist: torchvision==0.22.1
Requires-Dist: pytorch-model-summary==0.1.2
Requires-Dist: ollama==0.5.1
Requires-Dist: openai==1.97.1
Requires-Dist: asksageclient==1.31
Requires-Dist: dash[async]==3.1.1
Requires-Dist: fastapi[standard]==0.116.1
Requires-Dist: pydantic==2.11.7
Requires-Dist: starlette==0.47.2
Requires-Dist: uvicorn==0.35.0
Requires-Dist: hypercorn==0.17.3
Requires-Dist: sqlmodel==0.0.24
Requires-Dist: sqlalchemy==2.0.42
Requires-Dist: pydantic_settings==2.10.1
Requires-Dist: uuid-utils==0.11.0
Requires-Dist: dash_bootstrap_components==2.0.3
Requires-Dist: gunicorn[gevent]==23.0.0
Requires-Dist: certifi==2025.7.14
Dynamic: license-file
